imforge/__init__.py
imforge/crop.py
imforge/cut.py
imforge/utils.py
imforge-0.2.0.dist-info/LICENSE
imforge-0.2.0.dist-info/METADATA
imforge-0.2.0.dist-info/WHEEL
imforge-0.2.0.dist-info/top_level.txt
imforge-0.2.0.dist-info/RECORD
