Metadata-Version: 2.1
Name: imforge
Version: 0.2.0
Summary: Python IMage ENhanced TOols
Home-page: https://github.com/antoinehumbert/imforge
Author: Antoine HUMBERT
Author-email: antoine.humbert.dev@gmail.com
License: Apache License 2.0
Keywords: Imaging
Platform: UNKNOWN
Classifier: Development Status :: 5 - Production/Stable
Classifier: Programming Language :: Python :: 3
Classifier: License :: OSI Approved :: Apache Software License
Classifier: Operating System :: OS Independent
Classifier: Topic :: Multimedia :: Graphics
Requires-Python: >=3.6
Requires-Dist: pillow (~=8.1)
Requires-Dist: opencv-python-headless (~=4.5)
Requires-Dist: numpy (~=1.19)
Requires-Dist: pyclipper (~=1.2)
Provides-Extra: doc
Requires-Dist: sphinx ; extra == 'doc'
Requires-Dist: sphinx-rtd-theme ; extra == 'doc'
Provides-Extra: lint
Requires-Dist: flake8 ; extra == 'lint'
Provides-Extra: tests
Requires-Dist: pytest ; extra == 'tests'
Requires-Dist: pytest-cov ; extra == 'tests'
